{
  "pin_id": "37fe7585fe6c",
  "url": "https://in.pinterest.com/mohanty2922/rita-mota-fashion//pin/569438",
  "title": "Fashion Item 317",
  "description": "Beautiful fashion piece from rita-mota-fashion",
  "board_url": "https://in.pinterest.com/mohanty2922/rita-mota-fashion/",
  "board_name": "",
  "scraped_at": "2025-07-29T14:37:11.061897",
  "image_url": "https://i.pinimg.com/564x/92/47/12/sample.jpg",
  "tags": [
    "fashion",
    "style",
    "outfit"
  ],
  "ai_analysis": {
    "analyzed_at": "2025-07-29T14:37:11.563439",
    "fashion_items": [
      "dress",
      "accessories"
    ],
    "colors": [
      "blue",
      "white"
    ],
    "style": "casual",
    "season": "summer",
    "confidence": 0.85
  }
}